melpy/LinearRegression.py
melpy/NeuralNetworks.py
melpy/Tensor.py
melpy/__init__.py
melpy/callbacks.py
melpy/im2col.py
melpy/layers.py
melpy/losses.py
melpy/metrics.py
melpy/optimizers.py
melpy/preprocessing.py
melpy-1.2.3.0.dist-info/LICENSE
melpy-1.2.3.0.dist-info/METADATA
melpy-1.2.3.0.dist-info/WHEEL
melpy-1.2.3.0.dist-info/top_level.txt
melpy-1.2.3.0.dist-info/RECORD
