Metadata-Version: 2.1
Name: melpy
Version: 1.2.3.0
Summary: Melpy is a package made to learn deep learning.
Home-page: https://github.com/lennymalard/melpy-project
Author: Lenny Malard
Author-email: lennymalard@gmail.com
Classifier: Programming Language :: Python :: 3
Classifier: License :: OSI Approved :: MIT License
Classifier: Operating System :: OS Independent
Classifier: Development Status :: 1 - Planning
Classifier: Natural Language :: French
Classifier: Natural Language :: English
Classifier: Topic :: Scientific/Engineering :: Artificial Intelligence
Classifier: Topic :: Scientific/Engineering :: Information Analysis
Classifier: Topic :: Scientific/Engineering :: Mathematics
Classifier: Topic :: Scientific/Engineering :: Visualization
License-File: LICENSE
Requires-Dist: numpy >=1.18.0
Requires-Dist: matplotlib >=3.2.0
Requires-Dist: tqdm >=4.50.0
